vessim/__init__.py
vessim/_broker.py
vessim/_data.py
vessim/_util.py
vessim/actor.py
vessim/controller.py
vessim/environment.py
vessim/microgrid.py
vessim/plot.py
vessim/policy.py
vessim/signal.py
vessim/storage.py
vessim-0.13.1.dist-info/METADATA
vessim-0.13.1.dist-info/WHEEL
vessim-0.13.1.dist-info/licenses/LICENSE
vessim-0.13.1.dist-info/RECORD
