Metadata-Version: 2.4
Name: vessim
Version: 0.13.1
Summary: A simulator for carbon-aware applications and systems.
Author-email: Philipp Wiesner <wiesner@tu-berlin.de>
License-Expression: MIT
License-File: LICENSE
Keywords: carbon-aware computing,energy system,simulation,software-in-the-loop,testbed
Classifier: Development Status :: 3 - Alpha
Classifier: Intended Audience :: Developers
Classifier: Intended Audience :: Science/Research
Classifier: License :: OSI Approved :: MIT License
Classifier: Programming Language :: Python :: 3
Classifier: Programming Language :: Python :: 3 :: Only
Classifier: Programming Language :: Python :: 3.9
Classifier: Programming Language :: Python :: 3.10
Classifier: Programming Language :: Python :: 3.11
Classifier: Programming Language :: Python :: 3.12
Classifier: Programming Language :: Python :: 3.13
Classifier: Topic :: Education
Classifier: Topic :: Scientific/Engineering
Classifier: Topic :: Software Development :: Testing
Requires-Python: <3.14,>=3.9
Requires-Dist: docopt-ng>=0.9.0
Requires-Dist: loguru>=0.6.0
Requires-Dist: mosaik-api-v3>=3.0.4
Requires-Dist: mosaik>=3.3.0
Requires-Dist: numpy>=1.26.0
Requires-Dist: pandas>=2.0.0
Provides-Extra: dev
Requires-Dist: black; extra == 'dev'
Requires-Dist: mypy; extra == 'dev'
Requires-Dist: pandas-stubs; extra == 'dev'
Requires-Dist: pytest; extra == 'dev'
Requires-Dist: ruff; extra == 'dev'
Requires-Dist: types-psutil; extra == 'dev'
Requires-Dist: types-requests; extra == 'dev'
Provides-Extra: docs
Requires-Dist: mkdocs-material; extra == 'docs'
Requires-Dist: mkdocstrings[python]; extra == 'docs'
Requires-Dist: plotly; extra == 'docs'
Requires-Dist: setuptools; extra == 'docs'
Provides-Extra: sil
Requires-Dist: fastapi>=0.104.0; extra == 'sil'
Requires-Dist: prometheus-client>0.22.0; extra == 'sil'
Requires-Dist: requests>=2.26.0; extra == 'sil'
Requires-Dist: uvicorn>=0.23.0; extra == 'sil'
Provides-Extra: vis
Requires-Dist: plotly>=5.0.0; extra == 'vis'
Requires-Dist: streamlit>=1.28.0; extra == 'vis'
